{
  "youtube_id": "dN44xpHjNxE",
  "created_at": "2026-01-17T14:21:45.518490",
  "usage_count": 0,
  "source_url": "https://www.youtube.com/watch?v=dN44xpHjNxE",
  "quality": "balanced",
  "mode": "karaoke",
  "display_name": "Lukas Graham - Love Someone Official Music Video",
  "title": "Lukas Graham - Love Someone [Official Music Video]",
  "duration": 238,
  "is_youtube": true,
  "youtube_video_id": "dN44xpHjNxE",
  "has_video": true,
  "processed_at": "2026-01-17T14:21:45.518553",
  "music_info": 